{
    "Ar36": {
        "error": 0.004958594668020946,
        "error_type": "SEM",
        "filter_outliers_dict": {
            "filter_outliers": true,
            "iterations": 1,
            "std_devs": 3,
            "use_iqr_filtering": false,
            "use_standard_deviation_filtering": false
        },
        "fit": "linear",
        "fn": 339,
        "include_baseline_error": true,
        "n": 340,
        "outlier_excluded": [
            100
        ],
        "reviewed": true,
        "user_excluded": [],
        "value": 10.666786327823981
    },
    "Ar37": {
        "error": 0.007298150803278041,
        "error_type": "SEM",
        "filter_outliers_dict": {
            "filter_outliers": true,
            "iterations": 1,
            "std_devs": 3,
            "use_iqr_filtering": false,
            "use_standard_deviation_filtering": false
        },
        "fit": "linear",
        "fn": 338,
        "include_baseline_error": true,
        "n": 340,
        "outlier_excluded": [
            73,
            270
        ],
        "reviewed": true,
        "user_excluded": [],
        "value": 3.479711438581254
    },
    "Ar38": {
        "error": 0.002082775543976954,
        "error_type": "SEM",
        "filter_outliers_dict": {
            "filter_outliers": true,
            "iterations": 1,
            "std_devs": 3,
            "use_iqr_filtering": false,
            "use_standard_deviation_filtering": false
        },
        "fit": "linear",
        "fn": 339,
        "include_baseline_error": true,
        "n": 340,
        "outlier_excluded": [
            157
        ],
        "reviewed": true,
        "user_excluded": [],
        "value": 2.120542571144954
    },
    "Ar39": {
        "error": 0.014465423649161145,
        "error_type": "SEM",
        "filter_outliers_dict": {
            "filter_outliers": true,
            "iterations": 1,
            "std_devs": 3,
            "use_iqr_filtering": false,
            "use_standard_deviation_filtering": false
        },
        "fit": "parabolic",
        "fn": 339,
        "include_baseline_error": true,
        "n": 340,
        "outlier_excluded": [
            317
        ],
        "reviewed": true,
        "user_excluded": [],
        "value": 3.3068443213611025
    },
    "Ar40": {
        "error": 0.20205325316737777,
        "error_type": "SEM",
        "filter_outliers_dict": {
            "filter_outliers": true,
            "iterations": 1,
            "std_devs": 3,
            "use_iqr_filtering": false,
            "use_standard_deviation_filtering": false
        },
        "fit": "parabolic",
        "fn": 337,
        "include_baseline_error": true,
        "n": 340,
        "outlier_excluded": [
            0,
            245,
            191
        ],
        "reviewed": true,
        "user_excluded": [],
        "value": 3227.382806619734
    }
}