{
    "AX(CDD)": {
        "error": 7.113871494239452e-06,
        "error_type": "SEM",
        "filter_outliers_dict": {
            "filter_outliers": true,
            "iterations": 1,
            "std_devs": 2
        },
        "fit": "average",
        "modifier_error": 1.887177337389064e-05,
        "modifier_value": 0.00014033320725934868,
        "value": 0.00016181662804946867
    },
    "H1": {
        "error": 0.008609713637987987,
        "error_type": "SEM",
        "filter_outliers_dict": {
            "filter_outliers": true,
            "iterations": 1,
            "std_devs": 2
        },
        "fit": "average",
        "modifier_error": 0.0,
        "modifier_value": 0.0,
        "value": 0.09103141330126649
    },
    "H2": {
        "error": 0.013918550584540246,
        "error_type": "SEM",
        "filter_outliers_dict": {
            "filter_outliers": true,
            "iterations": 1,
            "std_devs": 2
        },
        "fit": "average",
        "modifier_error": 0.0,
        "modifier_value": 0.0,
        "value": 0.3580067895056038
    },
    "L1": {
        "error": 0.007078378868810881,
        "error_type": "SEM",
        "filter_outliers_dict": {
            "filter_outliers": true,
            "iterations": 1,
            "std_devs": 2
        },
        "fit": "average",
        "modifier_error": 0.0,
        "modifier_value": 0.0,
        "value": -0.019172537069844682
    },
    "L2(CDD)": {
        "error": 4.410971878716598e-22,
        "error_type": "SEM",
        "filter_outliers_dict": {
            "filter_outliers": true,
            "iterations": 1,
            "std_devs": 10
        },
        "fit": "average",
        "modifier_error": 4.993001914608499e-06,
        "modifier_value": 9.823324508154408e-06,
        "value": 9.823324508154412e-06
    }
}