{
    "Ar36": {
        "error": 0.0002708039611084346,
        "error_type": "SEM",
        "filter_outliers_dict": {
            "filter_outliers": true,
            "iterations": 1,
            "std_devs": 3,
            "use_iqr_filtering": false,
            "use_standard_deviation_filtering": false
        },
        "fit": "Parabolic",
        "fn": 279,
        "include_baseline_error": true,
        "n": 280,
        "outlier_excluded": [
            118
        ],
        "reviewed": true,
        "user_excluded": [],
        "value": 0.00897072011072698
    },
    "Ar37": {
        "error": 0.0038615351177329485,
        "error_type": "SEM",
        "filter_outliers_dict": {
            "filter_outliers": true,
            "iterations": 1,
            "std_devs": 3,
            "use_iqr_filtering": false,
            "use_standard_deviation_filtering": false
        },
        "fit": "Linear",
        "fn": 278,
        "include_baseline_error": true,
        "n": 280,
        "outlier_excluded": [
            60,
            45
        ],
        "reviewed": true,
        "user_excluded": [],
        "value": -0.017074408020204268
    },
    "Ar38": {
        "error": 0.0030616734289007643,
        "error_type": "SEM",
        "filter_outliers_dict": {
            "filter_outliers": true,
            "iterations": 1,
            "std_devs": 3,
            "use_iqr_filtering": false,
            "use_standard_deviation_filtering": false
        },
        "fit": "Linear",
        "fn": 280,
        "include_baseline_error": true,
        "n": 280,
        "outlier_excluded": [],
        "reviewed": true,
        "user_excluded": [],
        "value": 0.11891049298832672
    },
    "Ar39": {
        "error": 0.013693316048682446,
        "error_type": "SEM",
        "filter_outliers_dict": {
            "filter_outliers": true,
            "iterations": 1,
            "std_devs": 3,
            "use_iqr_filtering": false,
            "use_standard_deviation_filtering": false
        },
        "fit": "Parabolic",
        "fn": 280,
        "include_baseline_error": true,
        "n": 280,
        "outlier_excluded": [],
        "reviewed": true,
        "user_excluded": [],
        "value": 7.27627517152046
    },
    "Ar40": {
        "error": 0.013327681710945437,
        "error_type": "SEM",
        "filter_outliers_dict": {
            "filter_outliers": true,
            "iterations": 1,
            "std_devs": 3,
            "use_iqr_filtering": false,
            "use_standard_deviation_filtering": false
        },
        "fit": "Parabolic",
        "fn": 279,
        "include_baseline_error": true,
        "n": 280,
        "outlier_excluded": [
            227
        ],
        "reviewed": true,
        "user_excluded": [],
        "value": 31.78176626515327
    },
    "Ar41": {
        "error": 0.03402527796088792,
        "error_type": "SEM",
        "filter_outliers_dict": {
            "filter_outliers": true,
            "iterations": 1,
            "std_devs": 2
        },
        "fit": "linear",
        "value": -0.2548254635297625
    }
}