{
    "AX(CDD)": {
        "error": 7.965121306287422e-06,
        "error_type": "SEM",
        "filter_outliers_dict": {
            "filter_outliers": true,
            "iterations": 1,
            "std_devs": 2
        },
        "fit": "average",
        "modifier_error": 1.3444466929047529e-05,
        "modifier_value": 7.139299367350601e-05,
        "value": 0.0001004320243177784
    },
    "H1": {
        "error": 0.00695422016140744,
        "error_type": "SEM",
        "filter_outliers_dict": {
            "filter_outliers": true,
            "iterations": 1,
            "std_devs": 2
        },
        "fit": "average",
        "modifier_error": 0.0,
        "modifier_value": 0.0,
        "value": 0.03230507921112613
    },
    "H2": {
        "error": 0.01730819567302195,
        "error_type": "SEM",
        "filter_outliers_dict": {
            "filter_outliers": true,
            "iterations": 1,
            "std_devs": 2
        },
        "fit": "average",
        "modifier_error": 0.0,
        "modifier_value": 0.0,
        "value": 0.36384457618659916
    },
    "L1": {
        "error": 0.007670660908197285,
        "error_type": "SEM",
        "filter_outliers_dict": {
            "filter_outliers": true,
            "iterations": 1,
            "std_devs": 2
        },
        "fit": "average",
        "modifier_error": 0.0,
        "modifier_value": 0.0,
        "value": -0.01692307534730068
    },
    "L2(CDD)": {
        "error": 2.6041425420890165e-06,
        "error_type": "SEM",
        "filter_outliers_dict": {
            "filter_outliers": true,
            "iterations": 1,
            "std_devs": 10
        },
        "fit": "average",
        "modifier_error": 3.5570716004092026e-06,
        "modifier_value": 4.99750955714542e-06,
        "value": 7.601652099234435e-06
    }
}