{
    "AX(CDD)": {
        "error": 0.0027298249025612224,
        "fit": "Bracketing Interpolate",
        "reference_data": {
            "es": [
                0.0037166069200879797,
                0.0038423981478326037,
                0.0035267868533847137,
                0.0035886213862172367,
                0.003611559063421569,
                0.0039944096248175,
                0.0036988669178472824,
                0.0035033130548662193,
                0.003979313528373166,
                0.0037288176769415017,
                0.0036825302312522065,
                0.00373824582797043,
                0.0036126669679227732,
                0.003727114503657487,
                0.0035702716582729213,
                0.0038484629543775236,
                0.0037325759022271226,
                0.0034353547037314722,
                0.0035756697782746163,
                0.004027916657051896,
                0.0035831074158388836,
                0.003687032858457503,
                0.0036291284458364447,
                0.0037455253997191345,
                0.0043386799964944146,
                0.003997072312020806,
                0.003764034798951167,
                0.0038485938656672145,
                0.0038097574581267913,
                0.0038806504251186853,
                0.003840768298899266,
                0.003616001002538244,
                0.0037146572193755127,
                0.003735683004117462,
                0.0037171274345066457,
                0.003724800333715491,
                0.003747126868178599
            ],
            "vs": [
                1.011990328722237,
                1.011911824226655,
                1.0056704762173667,
                1.0026943624029268,
                1.0053808805262112,
                1.0072691121168589,
                1.0045876198878236,
                1.010034151801824,
                1.0087160955809373,
                1.0180133637620208,
                1.0073985035437927,
                1.0143310312021794,
                1.016214709993955,
                1.0174501859437088,
                1.0077700334597612,
                1.0086217844680307,
                1.0047179084633153,
                1.0067893998449002,
                1.0080674987446514,
                1.0086480851999589,
                1.007448560059166,
                1.0054453153027907,
                1.0091175316332592,
                1.007376870452946,
                1.0177851398684683,
                1.00505358657738,
                1.0176637179869226,
                1.0151112668453977,
                1.0152535162831928,
                1.0245446342076971,
                1.0113877940255929,
                1.0115657564243674,
                1.0067656821602657,
                1.0138351892712552,
                1.0145603484742178,
                1.006655536092988,
                1.0120504028439097
            ],
            "xs": [
                1711728313.0,
                1711728935.0,
                1711739380.0,
                1711748005.0,
                1711756155.0,
                1711762920.0,
                1711769693.0,
                1711776465.0,
                1711782351.0,
                1711788475.0,
                1711794171.0,
                1711801934.0,
                1711818138.0,
                1711818766.0,
                1711826000.0,
                1711833284.0,
                1711840537.0,
                1711847940.0,
                1711854641.0,
                1711903994.0,
                1711910564.0,
                1711919051.0,
                1711928413.0,
                1711938407.0,
                1711943244.0,
                1711943878.0,
                1711980182.0,
                1711989557.0,
                1711994832.0,
                1712005142.0,
                1712014354.0,
                1712021247.0,
                1712028259.0,
                1712034288.0,
                1712040777.0,
                1712046387.0,
                1712052290.0
            ]
        },
        "reference_detector": "H2",
        "references": [
            {
                "exclude": "omit",
                "record_id": "a-03-F-4674",
                "uuid": "df921295-ea8d-4afa-a8f9-daf72901b0ec"
            },
            {
                "exclude": "ok",
                "record_id": "a-03-F-4675",
                "uuid": "681e6312-062f-432e-b2a9-054b990ddd5e"
            },
            {
                "exclude": "ok",
                "record_id": "a-03-F-4676",
                "uuid": "de2dd022-1e0b-4329-9b67-96af06671d72"
            },
            {
                "exclude": "ok",
                "record_id": "a-03-F-4677",
                "uuid": "570232e4-6e73-4f01-93ad-040ebe5623e3"
            },
            {
                "exclude": "ok",
                "record_id": "a-03-F-4678",
                "uuid": "1901b14d-9cd2-42ba-9da2-96419d9049b5"
            },
            {
                "exclude": "ok",
                "record_id": "a-03-F-4679",
                "uuid": "f52a5e8f-c35d-4c55-b11f-e55931c48c03"
            },
            {
                "exclude": "ok",
                "record_id": "a-03-F-4680",
                "uuid": "ef8d4522-4b11-4668-a664-e98b9b416667"
            },
            {
                "exclude": "ok",
                "record_id": "a-03-F-4681",
                "uuid": "b557493b-93eb-4127-92bd-176c1530851f"
            },
            {
                "exclude": "ok",
                "record_id": "a-03-F-4682",
                "uuid": "94f21bf7-5836-476c-8c15-9e2ddb54d8d8"
            },
            {
                "exclude": "ok",
                "record_id": "a-03-F-4683",
                "uuid": "a84e40d3-c73a-43ac-a55d-731dc26f92b1"
            },
            {
                "exclude": "ok",
                "record_id": "a-03-F-4684",
                "uuid": "d1c0d02f-989e-488c-ade3-8a4c9a71a56a"
            },
            {
                "exclude": "ok",
                "record_id": "a-03-F-4685",
                "uuid": "3ed8eba7-e5bf-421a-9905-3733ad81aada"
            },
            {
                "exclude": "ok",
                "record_id": "a-03-F-4686",
                "uuid": "afba2469-e16f-4409-9862-55746b0ca204"
            },
            {
                "exclude": "ok",
                "record_id": "a-03-F-4687",
                "uuid": "285e1c34-d2ac-4df9-8025-e87de7546cba"
            },
            {
                "exclude": "ok",
                "record_id": "a-03-F-4688",
                "uuid": "f32205a4-f314-4e85-b768-3202289387a7"
            },
            {
                "exclude": "ok",
                "record_id": "a-03-F-4689",
                "uuid": "ac0e540f-7433-41cf-a68b-9ba5d2fa2271"
            },
            {
                "exclude": "ok",
                "record_id": "a-03-F-4690",
                "uuid": "96dfa3b8-0e9d-4e44-b74e-65aedde43d18"
            },
            {
                "exclude": "ok",
                "record_id": "a-03-F-4691",
                "uuid": "271c0c02-55e5-4d21-a63f-fe61e431cfa2"
            },
            {
                "exclude": "ok",
                "record_id": "a-03-F-4692",
                "uuid": "f40aea91-bd94-4a0a-938e-1b5f10aa91b8"
            },
            {
                "exclude": "ok",
                "record_id": "a-03-F-4693",
                "uuid": "883a88e6-3a8f-4842-a3b9-b482bf841366"
            },
            {
                "exclude": "ok",
                "record_id": "a-03-F-4694",
                "uuid": "b91241fe-8add-4c97-92cf-624195bd3c12"
            },
            {
                "exclude": "ok",
                "record_id": "a-03-F-4695",
                "uuid": "cb61d7eb-c5e3-42e9-9896-2af1fdf0a160"
            },
            {
                "exclude": "ok",
                "record_id": "a-03-F-4696",
                "uuid": "f3af297b-f738-48bb-8192-1b834a03e043"
            },
            {
                "exclude": "ok",
                "record_id": "a-03-F-4697",
                "uuid": "234f258d-dee3-4406-a2f1-344b53cb9908"
            },
            {
                "exclude": "omit",
                "record_id": "a-03-F-4698",
                "uuid": "ac846a55-927a-41d2-8c58-51f253017729"
            },
            {
                "exclude": "ok",
                "record_id": "a-03-F-4699",
                "uuid": "59de9a03-a4a2-47b4-8ca8-5ae297908015"
            },
            {
                "exclude": "ok",
                "record_id": "a-03-F-4700",
                "uuid": "4a718d2f-094e-4ebc-9e68-d3245123726d"
            },
            {
                "exclude": "ok",
                "record_id": "a-03-F-4701",
                "uuid": "d08c0fb8-16ef-45a2-9230-fc535def5352"
            },
            {
                "exclude": "ok",
                "record_id": "a-03-F-4702",
                "uuid": "1e117422-7155-469a-abf3-4a281c71897b"
            },
            {
                "exclude": "ok",
                "record_id": "a-03-F-4703",
                "uuid": "78797e96-f5d2-49fb-b651-649cd8e2f659"
            },
            {
                "exclude": "ok",
                "record_id": "a-03-F-4704",
                "uuid": "e646b5b4-398e-4dc2-a421-034968b25511"
            },
            {
                "exclude": "ok",
                "record_id": "a-03-F-4705",
                "uuid": "2fe0117c-ae36-4748-8e01-51cb5a63bdaa"
            },
            {
                "exclude": "ok",
                "record_id": "a-03-F-4706",
                "uuid": "fc5406db-2aad-4938-bf79-20398f4960b2"
            },
            {
                "exclude": "ok",
                "record_id": "a-03-F-4707",
                "uuid": "a27ac4c8-8a15-4eb0-8c4d-750daaf6fa87"
            },
            {
                "exclude": "ok",
                "record_id": "a-03-F-4708",
                "uuid": "d8dcb79a-12da-496c-b96c-8e22dd2039f9"
            },
            {
                "exclude": "ok",
                "record_id": "a-03-F-4709",
                "uuid": "841de066-2171-4cf5-bb43-24fe308c7341"
            },
            {
                "exclude": "ok",
                "record_id": "a-03-F-4710",
                "uuid": "1f72107c-d093-4b00-a344-404d806e10c9"
            }
        ],
        "reviewed": true,
        "standard_ratio": 1575.0,
        "value": 1.01789480269577
    },
    "H1": {
        "error": 0.0005287304893775064,
        "fit": "Weighted Mean",
        "reference_data": {
            "es": [
                0.0006316287263009437,
                0.0006271694976750195,
                0.0006308675682036817,
                0.0006455392351075793,
                0.0006489360414155906,
                0.0006495885054968348,
                0.0006444473425226028,
                0.0006226437064817402,
                0.0006216253615265468,
                0.0006475023577727739,
                0.0006377544699030635,
                0.0005860212488624359,
                0.0005972910956997431,
                0.000611440279805535,
                0.0006421961901725549,
                0.0006177725819633619,
                0.0006314320935415565,
                0.0006442600029372733,
                0.0006052473281978824,
                0.0006453994600446376,
                0.0006243873746430174,
                0.0006165962435849324,
                0.0006236979594652786,
                0.0005894290026582566,
                0.0006005862733993736,
                0.00066018623008988,
                0.0006496408083667715,
                0.0006402499684232975,
                0.0006481281150764126,
                0.0006727019665672627,
                0.000661450290658788,
                0.000613632621118829,
                0.0006222188214124085,
                0.0006515903861697497
            ],
            "vs": [
                1.0189470766117281,
                1.0185019681795024,
                1.0198355007491922,
                1.0205612815279228,
                1.0180792960217664,
                1.0194308318178755,
                1.018731111824224,
                1.0196970347506973,
                1.0178857328102293,
                1.0196934543007674,
                1.0200650830001428,
                1.0192928762006728,
                1.019357846592711,
                1.0197421854330824,
                1.0187742425138417,
                1.019214034252258,
                1.0199552536596486,
                1.0198061804877891,
                1.016979691829008,
                1.0180873004003226,
                1.0173656789080439,
                1.0184257557541085,
                1.020492897402311,
                1.018824637285357,
                1.0195035315925194,
                1.0203134762592598,
                1.021921051979726,
                1.0206958612807826,
                1.020436029381575,
                1.0196683232679238,
                1.0197340399789065,
                1.0189592295523235,
                1.0193260192060543,
                1.0191149085175246
            ],
            "xs": [
                1711729829.0,
                1711730397.0,
                1711738759.0,
                1711747383.0,
                1711755533.0,
                1711761972.0,
                1711769072.0,
                1711775843.0,
                1711781731.0,
                1711787530.0,
                1711793550.0,
                1711801311.0,
                1711819332.0,
                1711825358.0,
                1711832318.0,
                1711839894.0,
                1711847312.0,
                1711854015.0,
                1711903003.0,
                1711909939.0,
                1711918428.0,
                1711927787.0,
                1711937451.0,
                1711980734.0,
                1711988929.0,
                1711994188.0,
                1712005697.0,
                1712013712.0,
                1712020624.0,
                1712027306.0,
                1712033665.0,
                1712040154.0,
                1712045765.0,
                1712053154.0
            ]
        },
        "reference_detector": "H2",
        "references": [
            {
                "exclude": "ok",
                "record_id": "c-03-F-2580",
                "uuid": "c2c1cc64-f091-4981-9ae9-13f021bf97c5"
            },
            {
                "exclude": "ok",
                "record_id": "c-03-F-2581",
                "uuid": "06d03b74-0657-4f6c-922c-a7699fcc2256"
            },
            {
                "exclude": "ok",
                "record_id": "c-03-F-2582",
                "uuid": "2123d781-dbab-4b0d-8ba9-434a09487d42"
            },
            {
                "exclude": "ok",
                "record_id": "c-03-F-2583",
                "uuid": "bdfb6f28-759f-40f9-904d-206b87b3d4ac"
            },
            {
                "exclude": "ok",
                "record_id": "c-03-F-2584",
                "uuid": "1e83732a-9853-4e02-86be-0cbb98493627"
            },
            {
                "exclude": "ok",
                "record_id": "c-03-F-2585",
                "uuid": "7d7d4510-5ca0-4892-b3da-8cb809212b9c"
            },
            {
                "exclude": "ok",
                "record_id": "c-03-F-2586",
                "uuid": "bca24b46-e9d6-4285-a90a-74c7c30d38aa"
            },
            {
                "exclude": "ok",
                "record_id": "c-03-F-2587",
                "uuid": "6c3d47f0-3504-45d6-b6ad-e0403af131b2"
            },
            {
                "exclude": "ok",
                "record_id": "c-03-F-2588",
                "uuid": "bba9e9df-2cf1-46ac-a46a-f5a6434303d4"
            },
            {
                "exclude": "ok",
                "record_id": "c-03-F-2589",
                "uuid": "3b635fda-990b-4eb2-93c8-88c29577494f"
            },
            {
                "exclude": "ok",
                "record_id": "c-03-F-2590",
                "uuid": "1bd13eb4-4f35-4405-8d07-e82bbdba3dd3"
            },
            {
                "exclude": "ok",
                "record_id": "c-03-F-2591",
                "uuid": "ce59ac85-8fe7-4cd0-8f10-f74b9d6ee580"
            },
            {
                "exclude": "ok",
                "record_id": "c-03-F-2592",
                "uuid": "6f8301f7-a18e-4747-8988-7133a3f59435"
            },
            {
                "exclude": "ok",
                "record_id": "c-03-F-2593",
                "uuid": "c2882c3b-3b17-452f-a8a5-f2e0db15d7b6"
            },
            {
                "exclude": "ok",
                "record_id": "c-03-F-2594",
                "uuid": "d6b6a2e1-6916-435a-9234-054b661553db"
            },
            {
                "exclude": "ok",
                "record_id": "c-03-F-2595",
                "uuid": "261342b9-01bb-4fe1-a2a5-f7986659f076"
            },
            {
                "exclude": "ok",
                "record_id": "c-03-F-2596",
                "uuid": "62638247-ee13-4e2f-86f3-3cd2bd8fd642"
            },
            {
                "exclude": "ok",
                "record_id": "c-03-F-2597",
                "uuid": "5f56161c-f0e7-4b4d-adad-74888a1c60f9"
            },
            {
                "exclude": "ok",
                "record_id": "c-03-F-2598",
                "uuid": "910a62ac-1299-46de-aeb8-dd653cdc64d6"
            },
            {
                "exclude": "ok",
                "record_id": "c-03-F-2599",
                "uuid": "dda83469-5836-43a5-a4ff-4a4eee728654"
            },
            {
                "exclude": "ok",
                "record_id": "c-03-F-2600",
                "uuid": "7144e74d-1965-4f0d-bd8e-aef7b17143a3"
            },
            {
                "exclude": "ok",
                "record_id": "c-03-F-2601",
                "uuid": "177d0f51-3541-4309-bdf3-96452137405f"
            },
            {
                "exclude": "ok",
                "record_id": "c-03-F-2602",
                "uuid": "f7a9449e-a075-43df-b9e8-920f48bad3dc"
            },
            {
                "exclude": "ok",
                "record_id": "c-03-F-2603",
                "uuid": "72273ebb-38df-416a-85a4-fc710fbf5c23"
            },
            {
                "exclude": "ok",
                "record_id": "c-03-F-2604",
                "uuid": "fcf0c8ee-4e79-4a85-9183-4d15d597be91"
            },
            {
                "exclude": "ok",
                "record_id": "c-03-F-2605",
                "uuid": "25e16f3c-73ea-4f32-9899-c831e8c728ea"
            },
            {
                "exclude": "omit",
                "record_id": "c-03-F-2606",
                "uuid": "a05d9df9-688a-488e-91bf-ee3e343a8a40"
            },
            {
                "exclude": "ok",
                "record_id": "c-03-F-2607",
                "uuid": "325e40f1-51f7-4b67-beed-25f9cc90effa"
            },
            {
                "exclude": "ok",
                "record_id": "c-03-F-2608",
                "uuid": "cd7e7edf-1a48-4b68-bc24-0ec83f703684"
            },
            {
                "exclude": "ok",
                "record_id": "c-03-F-2609",
                "uuid": "2a3cc04f-dabc-452d-aa73-d74fbd6537f6"
            },
            {
                "exclude": "ok",
                "record_id": "c-03-F-2610",
                "uuid": "0a498a01-37be-4538-b6fe-1b3015f97064"
            },
            {
                "exclude": "ok",
                "record_id": "c-03-F-2611",
                "uuid": "463e6f1d-de25-41d2-bc39-2c5e7baac95a"
            },
            {
                "exclude": "ok",
                "record_id": "c-03-F-2612",
                "uuid": "8f7d803b-6cc4-4ca3-bf5b-902e156e0b2b"
            },
            {
                "exclude": "ok",
                "record_id": "c-03-F-2613",
                "uuid": "2d87f919-1f19-4ffb-812b-efbfec07dc0b"
            }
        ],
        "reviewed": true,
        "standard_ratio": 6.600975,
        "value": 1.0206192040909523
    },
    "H2": {
        "error": 1e-20,
        "fit": "default",
        "references": [],
        "value": 1.0
    },
    "L1": {
        "error": 1e-20,
        "fit": "default",
        "references": [],
        "value": 1.0
    },
    "L2(CDD)": {
        "error": 0.001095169541812375,
        "fit": "Bracketing Interpolate",
        "reference_data": {
            "es": [
                0.00148732431896711,
                0.0016303254839463814,
                0.001493260130964892,
                0.0016062471991645027,
                0.0017341960226281662,
                0.0015606060593776321,
                0.0015092628849069044,
                0.0016304313030670356,
                0.0015143769427554525,
                0.0016475676353609843,
                0.0016697412810513465,
                0.001575718048511719,
                0.0014779652096754959,
                0.0015872316510772927,
                0.0015164886640927184,
                0.001563580127855454,
                0.0016523779154364933,
                0.001509498300228123,
                0.0015813319971103622,
                0.0016534708889943553,
                0.0015500601208405663,
                0.001710985776287459,
                0.0015268000707102595,
                0.0015163239531235545,
                0.0021154793974643136,
                0.001567918556317163,
                0.001579468632843977,
                0.001658412926641715,
                0.0015223956514281106,
                0.001549340687545056,
                0.0015481105167601038,
                0.0015126958610312113,
                0.0016516981848838479,
                0.0015343049995068464,
                0.0015832424818908737,
                0.001671764811597074,
                0.0015480205494044423
            ],
            "vs": [
                0.9974119755099712,
                1.005506747004851,
                0.9942836417951592,
                0.9980772123003634,
                1.0009682964624895,
                1.000838547721359,
                0.9963789695307228,
                0.9975687468417739,
                1.004060677366718,
                1.0040532509621878,
                1.0027993204813717,
                1.0037261884764817,
                1.0010855023655545,
                1.0021970005147087,
                0.9976524707903907,
                0.9976414009557784,
                0.9975288654769743,
                1.0036223581366834,
                1.0017601157422356,
                0.9989746309483216,
                0.9981222953924553,
                0.9918798964420534,
                0.9978773202129533,
                0.9990803759475552,
                1.0624554989210107,
                0.9925148969398914,
                0.9947210275371301,
                0.9950112868389122,
                0.9949135530395172,
                1.0018731182900873,
                0.9991160478276332,
                0.9934134215380905,
                0.9961948899067051,
                0.9960650179556352,
                0.9971306667331863,
                0.9958699030596078,
                0.9958049118128978
            ],
            "xs": [
                1711728313.0,
                1711728935.0,
                1711739380.0,
                1711748005.0,
                1711756155.0,
                1711762920.0,
                1711769693.0,
                1711776465.0,
                1711782351.0,
                1711788475.0,
                1711794171.0,
                1711801934.0,
                1711818138.0,
                1711818766.0,
                1711826000.0,
                1711833284.0,
                1711840537.0,
                1711847940.0,
                1711854641.0,
                1711903994.0,
                1711910564.0,
                1711919051.0,
                1711928413.0,
                1711938407.0,
                1711943244.0,
                1711943878.0,
                1711980182.0,
                1711989557.0,
                1711994832.0,
                1712005142.0,
                1712014354.0,
                1712021247.0,
                1712028259.0,
                1712034288.0,
                1712040777.0,
                1712046387.0,
                1712052290.0
            ]
        },
        "reference_detector": "H2",
        "references": [
            {
                "exclude": "omit",
                "record_id": "a-03-F-4674",
                "uuid": "df921295-ea8d-4afa-a8f9-daf72901b0ec"
            },
            {
                "exclude": "ok",
                "record_id": "a-03-F-4675",
                "uuid": "681e6312-062f-432e-b2a9-054b990ddd5e"
            },
            {
                "exclude": "ok",
                "record_id": "a-03-F-4676",
                "uuid": "de2dd022-1e0b-4329-9b67-96af06671d72"
            },
            {
                "exclude": "ok",
                "record_id": "a-03-F-4677",
                "uuid": "570232e4-6e73-4f01-93ad-040ebe5623e3"
            },
            {
                "exclude": "ok",
                "record_id": "a-03-F-4678",
                "uuid": "1901b14d-9cd2-42ba-9da2-96419d9049b5"
            },
            {
                "exclude": "ok",
                "record_id": "a-03-F-4679",
                "uuid": "f52a5e8f-c35d-4c55-b11f-e55931c48c03"
            },
            {
                "exclude": "ok",
                "record_id": "a-03-F-4680",
                "uuid": "ef8d4522-4b11-4668-a664-e98b9b416667"
            },
            {
                "exclude": "ok",
                "record_id": "a-03-F-4681",
                "uuid": "b557493b-93eb-4127-92bd-176c1530851f"
            },
            {
                "exclude": "ok",
                "record_id": "a-03-F-4682",
                "uuid": "94f21bf7-5836-476c-8c15-9e2ddb54d8d8"
            },
            {
                "exclude": "ok",
                "record_id": "a-03-F-4683",
                "uuid": "a84e40d3-c73a-43ac-a55d-731dc26f92b1"
            },
            {
                "exclude": "ok",
                "record_id": "a-03-F-4684",
                "uuid": "d1c0d02f-989e-488c-ade3-8a4c9a71a56a"
            },
            {
                "exclude": "ok",
                "record_id": "a-03-F-4685",
                "uuid": "3ed8eba7-e5bf-421a-9905-3733ad81aada"
            },
            {
                "exclude": "ok",
                "record_id": "a-03-F-4686",
                "uuid": "afba2469-e16f-4409-9862-55746b0ca204"
            },
            {
                "exclude": "ok",
                "record_id": "a-03-F-4687",
                "uuid": "285e1c34-d2ac-4df9-8025-e87de7546cba"
            },
            {
                "exclude": "ok",
                "record_id": "a-03-F-4688",
                "uuid": "f32205a4-f314-4e85-b768-3202289387a7"
            },
            {
                "exclude": "ok",
                "record_id": "a-03-F-4689",
                "uuid": "ac0e540f-7433-41cf-a68b-9ba5d2fa2271"
            },
            {
                "exclude": "ok",
                "record_id": "a-03-F-4690",
                "uuid": "96dfa3b8-0e9d-4e44-b74e-65aedde43d18"
            },
            {
                "exclude": "ok",
                "record_id": "a-03-F-4691",
                "uuid": "271c0c02-55e5-4d21-a63f-fe61e431cfa2"
            },
            {
                "exclude": "ok",
                "record_id": "a-03-F-4692",
                "uuid": "f40aea91-bd94-4a0a-938e-1b5f10aa91b8"
            },
            {
                "exclude": "ok",
                "record_id": "a-03-F-4693",
                "uuid": "883a88e6-3a8f-4842-a3b9-b482bf841366"
            },
            {
                "exclude": "ok",
                "record_id": "a-03-F-4694",
                "uuid": "b91241fe-8add-4c97-92cf-624195bd3c12"
            },
            {
                "exclude": "ok",
                "record_id": "a-03-F-4695",
                "uuid": "cb61d7eb-c5e3-42e9-9896-2af1fdf0a160"
            },
            {
                "exclude": "ok",
                "record_id": "a-03-F-4696",
                "uuid": "f3af297b-f738-48bb-8192-1b834a03e043"
            },
            {
                "exclude": "ok",
                "record_id": "a-03-F-4697",
                "uuid": "234f258d-dee3-4406-a2f1-344b53cb9908"
            },
            {
                "exclude": "omit",
                "record_id": "a-03-F-4698",
                "uuid": "ac846a55-927a-41d2-8c58-51f253017729"
            },
            {
                "exclude": "ok",
                "record_id": "a-03-F-4699",
                "uuid": "59de9a03-a4a2-47b4-8ca8-5ae297908015"
            },
            {
                "exclude": "ok",
                "record_id": "a-03-F-4700",
                "uuid": "4a718d2f-094e-4ebc-9e68-d3245123726d"
            },
            {
                "exclude": "ok",
                "record_id": "a-03-F-4701",
                "uuid": "d08c0fb8-16ef-45a2-9230-fc535def5352"
            },
            {
                "exclude": "ok",
                "record_id": "a-03-F-4702",
                "uuid": "1e117422-7155-469a-abf3-4a281c71897b"
            },
            {
                "exclude": "ok",
                "record_id": "a-03-F-4703",
                "uuid": "78797e96-f5d2-49fb-b651-649cd8e2f659"
            },
            {
                "exclude": "ok",
                "record_id": "a-03-F-4704",
                "uuid": "e646b5b4-398e-4dc2-a421-034968b25511"
            },
            {
                "exclude": "ok",
                "record_id": "a-03-F-4705",
                "uuid": "2fe0117c-ae36-4748-8e01-51cb5a63bdaa"
            },
            {
                "exclude": "ok",
                "record_id": "a-03-F-4706",
                "uuid": "fc5406db-2aad-4938-bf79-20398f4960b2"
            },
            {
                "exclude": "ok",
                "record_id": "a-03-F-4707",
                "uuid": "a27ac4c8-8a15-4eb0-8c4d-750daaf6fa87"
            },
            {
                "exclude": "ok",
                "record_id": "a-03-F-4708",
                "uuid": "d8dcb79a-12da-496c-b96c-8e22dd2039f9"
            },
            {
                "exclude": "ok",
                "record_id": "a-03-F-4709",
                "uuid": "841de066-2171-4cf5-bb43-24fe308c7341"
            },
            {
                "exclude": "ok",
                "record_id": "a-03-F-4710",
                "uuid": "1f72107c-d093-4b00-a344-404d806e10c9"
            }
        ],
        "reviewed": true,
        "standard_ratio": 295.5,
        "value": 1.0004796184992513
    }
}