{
    "AX": {
        "error": 0.004737396749096129, 
        "filter_outliers_dict": {
            "filter_outliers": true, 
            "iterations": 1, 
            "std_devs": 2
        }, 
        "fit": "average", 
        "value": 0.10588133994589127
    }, 
    "CDD": {
        "error": 3.1871810535274685e-06, 
        "filter_outliers_dict": {
            "filter_outliers": true, 
            "iterations": 1, 
            "std_devs": 10
        }, 
        "fit": "average", 
        "value": 8.653464453086717e-06
    }, 
    "H1": {
        "error": 0.0037693657095623297, 
        "filter_outliers_dict": {
            "filter_outliers": true, 
            "iterations": 1, 
            "std_devs": 2
        }, 
        "fit": "average", 
        "value": 0.07454416216740344
    }, 
    "H2": {
        "error": 0.003138143376665533, 
        "filter_outliers_dict": {
            "filter_outliers": true, 
            "iterations": 1, 
            "std_devs": 2
        }, 
        "fit": "average", 
        "value": -0.0886173034911528
    }, 
    "L1": {
        "error": 0.002083174882649524, 
        "filter_outliers_dict": {
            "filter_outliers": true, 
            "iterations": 1, 
            "std_devs": 2
        }, 
        "fit": "average", 
        "value": -0.034328533097499524
    }, 
    "L2": {
        "error": 0.004047891542178652, 
        "filter_outliers_dict": {
            "filter_outliers": true, 
            "iterations": 1, 
            "std_devs": 2
        }, 
        "fit": "average", 
        "value": 0.00838707306966874
    }
}