{
    "AX": {
        "error": 0.004456068605231506, 
        "filter_outliers_dict": {
            "filter_outliers": true, 
            "iterations": 1, 
            "std_devs": 2
        }, 
        "fit": "average", 
        "value": 0.09893856916649636
    }, 
    "CDD": {
        "error": 4.576626542332349e-06, 
        "filter_outliers_dict": {
            "filter_outliers": true, 
            "iterations": 1, 
            "std_devs": 10
        }, 
        "fit": "average", 
        "value": 1.607071972216844e-05
    }, 
    "H1": {
        "error": 0.0034303850135767693, 
        "filter_outliers_dict": {
            "filter_outliers": true, 
            "iterations": 1, 
            "std_devs": 2
        }, 
        "fit": "average", 
        "value": 0.08123039011877319
    }, 
    "H2": {
        "error": 0.0029429041759739, 
        "filter_outliers_dict": {
            "filter_outliers": true, 
            "iterations": 1, 
            "std_devs": 2
        }, 
        "fit": "average", 
        "value": -0.09663410938140535
    }, 
    "L1": {
        "error": 0.002062355744724897, 
        "filter_outliers_dict": {
            "filter_outliers": true, 
            "iterations": 1, 
            "std_devs": 2
        }, 
        "fit": "average", 
        "value": -0.037341400551779744
    }, 
    "L2": {
        "error": 0.003826024630850548, 
        "filter_outliers_dict": {
            "filter_outliers": true, 
            "iterations": 1, 
            "std_devs": 2
        }, 
        "fit": "average", 
        "value": 5.1487295350606436e-05
    }
}