{
    "Ar36": {
        "error": 0.000336274225841033,
        "error_type": "SEM",
        "filter_outliers_dict": {
            "filter_outliers": true,
            "iterations": 1,
            "std_devs": 3,
            "use_iqr_filtering": false,
            "use_standard_deviation_filtering": false
        },
        "fit": "linear",
        "fn": 340,
        "include_baseline_error": true,
        "n": 340,
        "outlier_excluded": [],
        "reviewed": true,
        "user_excluded": [],
        "value": 0.04352874152015408
    },
    "Ar37": {
        "error": 0.007845121892451196,
        "error_type": "SEM",
        "filter_outliers_dict": {
            "filter_outliers": true,
            "iterations": 1,
            "std_devs": 3,
            "use_iqr_filtering": false,
            "use_standard_deviation_filtering": false
        },
        "fit": "linear",
        "fn": 339,
        "include_baseline_error": true,
        "n": 340,
        "outlier_excluded": [
            17
        ],
        "reviewed": true,
        "user_excluded": [],
        "value": 9.316917233204512
    },
    "Ar38": {
        "error": 0.0006859562406171494,
        "error_type": "SEM",
        "filter_outliers_dict": {
            "filter_outliers": true,
            "iterations": 1,
            "std_devs": 3,
            "use_iqr_filtering": false,
            "use_standard_deviation_filtering": false
        },
        "fit": "linear",
        "fn": 339,
        "include_baseline_error": true,
        "n": 340,
        "outlier_excluded": [
            279
        ],
        "reviewed": true,
        "user_excluded": [],
        "value": 0.20575869018289794
    },
    "Ar39": {
        "error": 0.008105486393240708,
        "error_type": "SEM",
        "filter_outliers_dict": {
            "filter_outliers": true,
            "iterations": 1,
            "std_devs": 2,
            "use_iqr_filtering": false,
            "use_standard_deviation_filtering": false
        },
        "fit": "linear",
        "fn": 321,
        "include_baseline_error": true,
        "n": 340,
        "outlier_excluded": [
            262,
            263,
            139,
            283,
            302,
            52,
            61,
            318,
            191,
            64,
            192,
            193,
            209,
            89,
            90,
            100,
            104,
            242,
            245
        ],
        "reviewed": true,
        "user_excluded": [],
        "value": 18.80227015993531
    },
    "Ar40": {
        "error": 0.025633842218327263,
        "error_type": "SEM",
        "filter_outliers_dict": {
            "filter_outliers": true,
            "iterations": 1,
            "std_devs": 2,
            "use_iqr_filtering": false,
            "use_standard_deviation_filtering": false
        },
        "fit": "parabolic",
        "fn": 323,
        "include_baseline_error": true,
        "n": 340,
        "outlier_excluded": [
            32,
            289,
            323,
            197,
            134,
            294,
            136,
            104,
            171,
            300,
            188,
            274,
            311,
            284,
            215,
            156,
            93
        ],
        "reviewed": true,
        "user_excluded": [],
        "value": 12.034601221057207
    }
}